linguadoc/__init__.py
linguadoc/_entry.py
linguadoc/de/de_doc_cover.jpg
linguadoc/de/de_doc_end.jpg
linguadoc/de/de_template.docx
linguadoc/en/en_doc_cover.jpg
linguadoc/en/en_doc_end.jpg
linguadoc/en/en_template.docx
linguadoc/es/es_doc_cover.jpg
linguadoc/es/es_doc_end.jpg
linguadoc/es/es_template.docx
linguadoc/gen_doc.py
linguadoc/lib.py
linguadoc-0.1.5.dist-info/entry_points.txt
linguadoc-0.1.5.dist-info/WHEEL
linguadoc-0.1.5.dist-info/METADATA
linguadoc-0.1.5.dist-info/RECORD
