Metadata-Version: 2.1
Name: linguadoc
Version: 0.1.5
Summary: DOC generator for language learning
Home-page: https://github.com/qishe-nlp/linguadoc
Keywords: doc,language,auto
Author: Phoenix Grey
Author-email: phoenix.grey0108@gmail.com
Requires-Python: >=3.8,<4.0
Classifier: Programming Language :: Python :: 3
Classifier: Programming Language :: Python :: 3.10
Classifier: Programming Language :: Python :: 3.8
Classifier: Programming Language :: Python :: 3.9
Requires-Dist: click (>=8.0.3,<9.0.0)
Requires-Dist: python-docx (>=0.8.11,<0.9.0)
Project-URL: Documentation, https://qishe-nlp.github.io/linguadoc/
Project-URL: Repository, https://github.com/qishe-nlp/linguadoc
